{
  "main": {
    "id": "2019eef35aa5b7bf",
    "type": "split",
    "children": [
      {
        "id": "081999006ad5069c",
        "type": "tabs",
        "children": [
          {
            "id": "0d1302336a44d359",
            "type": "leaf",
            "state": {
              "type": "markdown",
              "state": {
                "file": "MachineLearning/FeatureEngineering/Normalisation.md",
                "mode": "preview",
                "backlinks": false,
                "source": false
              }
            }
          },
          {
            "id": "a6ffcf7baf129bf4",
            "type": "leaf",
            "state": {
              "type": "markdown",
              "state": {
                "file": "MachineLearning/ErrorMeasures/Confusion_matrices.md",
                "mode": "preview",
                "backlinks": false,
                "source": false
              }
            }
          },
          {
            "id": "5e9596bb5df94775",
            "type": "leaf",
            "state": {
              "type": "markdown",
              "state": {
                "file": "MachineLearning/0-CoursesPart2/StatisticalLearning_book/TreeBased_modeling.md",
                "mode": "source",
                "backlinks": false,
                "source": false
              }
            }
          },
          {
            "id": "04078575d632a274",
            "type": "leaf",
            "state": {
              "type": "markdown",
              "state": {
                "file": "MachineLearning/0-GeneralConcepts/ML_tuning/End_to_end_learning.md",
                "mode": "source",
                "backlinks": false,
                "source": false
              }
            }
          },
          {
            "id": "77bd044de66a837c",
            "type": "leaf",
            "state": {
              "type": "markdown",
              "state": {
                "file": "MachineLearning/Neural_networks.md",
                "mode": "preview",
                "backlinks": false,
                "source": false
              }
            }
          },
          {
            "id": "7d186001ec769efd",
            "type": "leaf",
            "state": {
              "type": "markdown",
              "state": {
                "file": "MachineLearning/Decision_trees.md",
                "mode": "preview",
                "backlinks": false,
                "source": false
              }
            }
          },
          {
            "id": "13e60f27d5180f43",
            "type": "leaf",
            "state": {
              "type": "markdown",
              "state": {
                "file": "MachineLearning/K-nearest_neighbours.md",
                "mode": "source",
                "backlinks": false,
                "source": false
              }
            }
          },
          {
            "id": "1b4c91849cb47f78",
            "type": "leaf",
            "state": {
              "type": "markdown",
              "state": {
                "file": "MachineLearning/0-GeneralConcepts/TreeModels/Decision_Trees_legacy.md",
                "mode": "preview",
                "backlinks": false,
                "source": false
              }
            }
          },
          {
            "id": "ac3a88623f86b424",
            "type": "leaf",
            "state": {
              "type": "markdown",
              "state": {
                "file": "MachineLearning/Gradient_descent.md",
                "mode": "preview",
                "backlinks": false,
                "source": false
              }
            }
          },
          {
            "id": "104a3df6583cb039",
            "type": "leaf",
            "state": {
              "type": "markdown",
              "state": {
                "file": "MachineLearning/0-CoursesPart1/MachineLearning/ML_error_analysis.md",
                "mode": "source",
                "backlinks": false,
                "source": false
              }
            }
          },
          {
            "id": "6a7e0100d89f7458",
            "type": "leaf",
            "state": {
              "type": "markdown",
              "state": {
                "file": "MachineLearning/ClusteringAlgorithms/Clustering.md",
                "mode": "source",
                "backlinks": false,
                "source": false
              }
            }
          },
          {
            "id": "794011006bf4112b",
            "type": "leaf",
            "state": {
              "type": "markdown",
              "state": {
                "file": "MachineLearning/ClusteringAlgorithms/Clustering.md",
                "mode": "preview",
                "backlinks": false,
                "source": false
              }
            }
          },
          {
            "id": "98fc0f1206756e63",
            "type": "leaf",
            "state": {
              "type": "markdown",
              "state": {
                "file": "MachineLearning/0-CoursesPart1/MachineLearning/K-Means_algorithm.md",
                "mode": "source",
                "backlinks": false,
                "source": false
              }
            }
          },
          {
            "id": "a1548c4c116594bb",
            "type": "leaf",
            "state": {
              "type": "markdown",
              "state": {
                "file": "MachineLearning/ClusteringAlgorithms/Hierarchal_clustering.md",
                "mode": "preview",
                "backlinks": false,
                "source": false
              }
            }
          },
          {
            "id": "cb6e0741d547e3c3",
            "type": "leaf",
            "state": {
              "type": "markdown",
              "state": {
                "file": "MachineLearning/ClusteringAlgorithms/K-means_clustering.md",
                "mode": "preview",
                "backlinks": false,
                "source": false
              }
            }
          },
          {
            "id": "731effe322a9679d",
            "type": "leaf",
            "state": {
              "type": "markdown",
              "state": {
                "file": "MachineLearning/FeatureEngineering/Machine_learning_features.md",
                "mode": "preview",
                "backlinks": false,
                "source": false
              }
            }
          }
        ],
        "currentTab": 5
      }
    ],
    "direction": "vertical"
  },
  "left": {
    "id": "72a38283dfdda09c",
    "type": "split",
    "children": [
      {
        "id": "686f58e7afd14325",
        "type": "tabs",
        "dimension": 73.95061728395062,
        "children": [
          {
            "id": "61b6b073dac95afd",
            "type": "leaf",
            "state": {
              "type": "file-explorer",
              "state": {
                "sortOrder": "alphabetical"
              }
            }
          },
          {
            "id": "43d3ffa91ddc39a4",
            "type": "leaf",
            "state": {
              "type": "search",
              "state": {
                "query": "",
                "matchingCase": false,
                "explainSearch": false,
                "collapseAll": true,
                "extraContext": false,
                "sortOrder": "alphabetical"
              }
            }
          },
          {
            "id": "d10fc8b81a0120b7",
            "type": "leaf",
            "state": {
              "type": "bookmarks",
              "state": {}
            }
          },
          {
            "id": "4551ace807986438",
            "type": "leaf",
            "state": {
              "type": "tagfolder-view",
              "state": {}
            }
          }
        ]
      },
      {
        "id": "3c8c11216e62f58c",
        "type": "tabs",
        "dimension": 26.049382716049386,
        "children": [
          {
            "id": "f9ef0de97216c2fd",
            "type": "leaf",
            "state": {
              "type": "outline",
              "state": {
                "file": "MachineLearning/Decision_trees.md"
              }
            }
          }
        ]
      }
    ],
    "direction": "horizontal",
    "width": 398.5041847229004,
    "collapsed": true
  },
  "right": {
    "id": "441e4249d5592193",
    "type": "split",
    "children": [
      {
        "id": "bd313b46553a0492",
        "type": "tabs",
        "children": [
          {
            "id": "9863ed448e0c5948",
            "type": "leaf",
            "state": {
              "type": "tag",
              "state": {
                "sortOrder": "frequency",
                "useHierarchy": false
              }
            }
          },
          {
            "id": "60e33f4ffe05ae46",
            "type": "leaf",
            "state": {
              "type": "backlink",
              "state": {
                "file": "MachineLearning/Decision_trees.md",
                "collapseAll": false,
                "extraContext": false,
                "sortOrder": "alphabetical",
                "showSearch": false,
                "searchQuery": "",
                "backlinkCollapsed": false,
                "unlinkedCollapsed": true
              }
            }
          },
          {
            "id": "b279bdfd2daa54f5",
            "type": "leaf",
            "state": {
              "type": "outgoing-link",
              "state": {
                "file": "MachineLearning/Decision_trees.md",
                "linksCollapsed": false,
                "unlinkedCollapsed": true
              }
            }
          },
          {
            "id": "85244c468e1bf2b5",
            "type": "leaf",
            "state": {
              "type": "Saved Queries View",
              "state": {}
            }
          },
          {
            "id": "608fb9c28a7b204a",
            "type": "leaf",
            "state": {
              "type": "graph-analysis",
              "state": {}
            }
          },
          {
            "id": "e33f6a0e5af10aaf",
            "type": "leaf",
            "state": {
              "type": "all-properties",
              "state": {
                "sortOrder": "frequency",
                "showSearch": false,
                "searchQuery": ""
              }
            }
          },
          {
            "id": "a7770745c2640108",
            "type": "leaf",
            "state": {
              "type": "advanced-tables-toolbar",
              "state": {}
            }
          }
        ],
        "currentTab": 6
      }
    ],
    "direction": "horizontal",
    "width": 200,
    "collapsed": true
  },
  "left-ribbon": {
    "hiddenItems": {
      "switcher:Open quick switcher": true,
      "graph:Open graph view": false,
      "canvas:Create new canvas": false,
      "command-palette:Open command palette": false,
      "markdown-importer:Open format converter": true,
      "random-note:Open random note": false,
      "oz-clear-unused-images:Clear Unused Images": false,
      "table-editor-obsidian:Advanced Tables Toolbar": false,
      "templater-obsidian:Templater": false,
      "omnisearch:Omnisearch": false
    }
  },
  "active": "7d186001ec769efd",
  "lastOpenFiles": [
    "XX-Attachments/Images/Pasted image 20240403184944.png",
    "MachineLearning/Neural_networks.md",
    "MachineLearning/Softmax.md",
    "MachineLearning/GeneticAlgorithms/Genetic_encoding.md",
    "MachineLearning/GeneticAlgorithms/Crossover.md",
    "MachineLearning/GeneticAlgorithms/Genetic_algorithms.md",
    "MachineLearning/GeneticAlgorithms/Genetic_selection.md",
    "MachineLearning/GeneticAlgorithms/Mutation.md",
    "MachineLearning/Activation_functions.md",
    "MachineLearning/Artificial_intelligence.md",
    "MachineLearning/FeatureEngineering/Normalisation.md",
    "MachineLearning/FeatureEngineering/Machine_learning_features.md",
    "MachineLearning/FeatureEngineering/FeatureSelectionMetrics/Pointwise_mutual_information.md",
    "MachineLearning/FeatureEngineering/FeatureSelectionMetrics/Term_frequency-inverse_document_frequency.md",
    "MachineLearning/ErrorMeasures/Model_metrics.md",
    "MachineLearning/ErrorMeasures/Confusion_matrices.md",
    "MachineLearning/ClusteringAlgorithms/Untitled.md",
    "MachineLearning/ClusteringAlgorithms/K-means_clustering.md",
    "MachineLearning/ClusteringAlgorithms/Hierarchal_clustering.md",
    "MachineLearning/ClusteringAlgorithms/Clustering.md",
    "MachineLearning/0-GeneralConcepts/TreeModels/Regression_trees.md",
    "MachineLearning/0-GeneralConcepts/TreeModels/Random_forests.md",
    "MachineLearning/0-GeneralConcepts/TreeModels/Decision_Trees_legacy.md",
    "MachineLearning/FeatureEngineering/Untitled.md",
    "MachineLearning/Decision_trees.md",
    "MachineLearning/0-GeneralConcepts/ML_tuning/End_to_end_learning.md",
    "XX-Attachments/Images/Pasted image 20240403004506.png",
    "XX-Attachments/Images/Pasted image 20240403004427.png",
    "XX-Attachments/Images/Pasted image 20240403004405.png",
    "XX-Attachments/Images/Pasted image 20240403004339.png",
    "XX-Attachments/Images/Pasted image 20240403004313.png",
    "XX-Attachments/Images/Pasted image 20240403000814.png",
    "XX-Attachments/Images/Pasted image 20240402230238.png",
    "XX-Attachments/Images/Pasted image 20240402224744.png",
    "XX-Attachments/Images/Pasted image 20240402224313.png",
    "XX-Attachments/Images/Pasted image 20240402223242.png",
    "MachineLearning/ClusteringAlgorithms",
    "MachineLearning/ErrorMeasures",
    "MediaCoding/Watermarking",
    "MediaCoding/DiscreteCosineTansform",
    "LinearAlgebra",
    "MediaCoding/OpticalFlow",
    "MediaCoding/ImageMatching",
    "MediaCoding/Filters/SmoothingFilters",
    "MediaCoding/Filters/EdgeDetectionFilters",
    "MediaCoding/Filters"
  ]
}